chatbot.py
setup.py
chatbot.egg-info/PKG-INFO
chatbot.egg-info/SOURCES.txt
chatbot.egg-info/dependency_links.txt
chatbot.egg-info/top_level.txt