Metadata-Version: 1.1
Name: chatbot
Version: 1.4.2b
Summary: Allows users on wikia wikis to create a chatbot for Special:Chat
Home-page: http://packages.python.org/chatbot/
Author: Matthew Cunningham
Author-email: hairrazerrr@gmail.com
License: MIT License
Download-URL: https://github.com/hairr/chatbot/archive/master.zip
Keywords: hairr wikia xhr chat bot
Platform: UNKNOWN
Classifier: Development Status :: 4 - Beta
Classifier: Environment :: Console
Classifier: Intended Audience :: Developers
Classifier: License :: OSI Approved :: MIT License
Classifier: Operating System :: OS Independent
Classifier: Programming Language :: Python :: 2.7
Classifier: Topic :: Communications :: Chat
Requires: r
Requires: e
Requires: q
Requires: u
Requires: e
Requires: s
Requires: t
Requires: s
